{"Title":"Stray Dogs","Year":"2004","Rated":"N/A","Released":"15 Jun 2005","Runtime":"93 min","Genre":"Drama","Director":"Marzieh Makhmalbaf","Writer":"Marzieh Makhmalbaf","Actors":"Gol-Ghotai, Zahed, Agheleh Rezaie, Sohrab Akbari","Plot":"The story of survival of 2 children in post-Taliban Afghanistan. Their mother has been imprisoned for \"adultery\" and their father is in Guantanamo Bay.","Language":"Dari","Country":"Iran, France, Afghanistan","Awards":"3 wins & 4 nominations.","Poster":"https://images-na.ssl-images-amazon.com/images/M/MV5BNzZjOTk3YjUtYjBiNi00ZjI5LWI5NjItMGExMjUwYjUxZGU5XkEyXkFqcGdeQXVyMjgxNDM5MDA@._V1_SX300.jpg","Ratings":[{"Source":"Internet Movie Database","Value":"7.2/10"}],"Metascore":"N/A","imdbRating":"7.2","imdbVotes":"464","imdbID":"tt0423277","Type":"movie","DVD":"N/A","BoxOffice":"N/A","Production":"Bac Films","Website":"N/A","Response":"True"}