{"Title":"Shootout at Lokhandwala","Year":"2007","Rated":"N/A","Released":"25 May 2007","Runtime":"122 min","Genre":"Action, Crime","Director":"Apoorva Lakhia","Writer":"Apoorva Lakhia, Suresh Nair, Raj Vasant (Dialogue)","Actors":"Amitabh Bachchan, Sanjay Dutt, Sunil Shetty, Arbaaz Khan","Plot":"An account of the gangster Mahindra Dolas and his gang, which terrorized Mumbai City, and a massive war between Mumbai Police and gangs during 16 November 1991.","Language":"Hindi","Country":"India","Awards":"3 wins & 1 nomination.","Poster":"https://m.media-amazon.com/images/M/MV5BNDNhNTI0NmItMzE0NS00ZDljLWI1YjktOGM0OTU5NjljZjFmXkEyXkFqcGdeQXVyODE5NzE3OTE@._V1_SX300.jpg","Ratings":[{"Source":"Internet Movie Database","Value":"7.1/10"}],"Metascore":"N/A","imdbRating":"7.1","imdbVotes":"8,214","imdbID":"tt0811066","Type":"movie","DVD":"12 Jul 2007","BoxOffice":"$289,232","Production":"N/A","Website":"N/A","Response":"True"}