{"Title":"Sell Out! (The Student Films of Don Swanson)","Year":"2007","Rated":"NOT RATED","Released":"05 Nov 2007","Runtime":"180 min","Genre":"Comedy, Drama, Horror","Director":"Don Swanson","Writer":"Don Swanson","Actors":"Amanda Black, John F. Blake, Richard D. Bowser, Chance E. Cann","Plot":"10 short films by award-winning indie filmmaker Don Swanson. This compilation includes film festival favorites & indie underground cult classics Wilson's Woodworkers, 2nd Class Citizen, ...","Language":"English","Country":"USA","Awards":"N/A","Poster":"http://ia.media-imdb.com/images/M/MV5BMTIyMzA5MjQ5NF5BMl5BanBnXkFtZTcwMTIyMTA4MQ@@._V1_SX300.jpg","Ratings":[{"Source":"Internet Movie Database","Value":"7.2/10"}],"Metascore":"N/A","imdbRating":"7.2","imdbVotes":"8","imdbID":"tt1140875","Type":"movie","DVD":"N/A","BoxOffice":"N/A","Production":"N/A","Website":"N/A","Response":"True"}