{"Title":"Iraq: Part Two","Year":"2010","Rated":"TV-MA","Released":"05 May 2010","Season":"1","Episode":"2","Runtime":"45 min","Genre":"Action, Drama, Thriller","Director":"Daniel Percival","Writer":"Jed Mercurio","Actors":"Philip Winchester, Sullivan Stapleton, Richard Armitage, Amanda Mealing","Plot":"Seven years after the events of part one, Porter is reactivated and tasked with rescuing a kidnapped reporter Katie Dartmouth. Porter realizes that Katie was kidnapped by the same ...","Language":"English, Arabic","Country":"UK, South Africa","Awards":"N/A","Poster":"https://images-na.ssl-images-amazon.com/images/M/MV5BMTc3MzkxMDU5N15BMl5BanBnXkFtZTgwNTM0NDc3MjE@._V1_SX300.jpg","Ratings":[{"Source":"Internet Movie Database","Value":"8.3/10"}],"Metascore":"N/A","imdbRating":"8.3","imdbVotes":"422","imdbID":"tt1497811","seriesID":"tt1492179","Type":"episode","Response":"True"}