{"Title":"The Crab","Year":"2010","Rated":"N/A","Released":"01 Jun 2010","Runtime":"103 min","Genre":"Comedy","Director":"Rona Mark","Writer":"Rona Mark","Actors":"Donella Alanwick, Dylan Nichole Bandy, Darrin Banks, Cass Buggé","Plot":"Levi is a washed-up academic who uses his genetic disorder - ectrodactyly, or lobster claw syndrome - as an excuse for across-the-board bitterness and rage. Hope surfaces when he meets ...","Language":"English","Country":"USA","Awards":"N/A","Poster":"https://images-na.ssl-images-amazon.com/images/M/MV5BMTk5NzQ4ODUxMV5BMl5BanBnXkFtZTcwMzc4MTMyNw@@._V1_SX300.jpg","Ratings":[{"Source":"Internet Movie Database","Value":"7.9/10"}],"Metascore":"N/A","imdbRating":"7.9","imdbVotes":"31","imdbID":"tt1570340","Type":"movie","DVD":"N/A","BoxOffice":"N/A","Production":"N/A","Website":"N/A","Response":"True"}