{"Title":"Waar","Year":"2013","Rated":"N/A","Released":"16 Oct 2013","Runtime":"130 min","Genre":"Action, Crime, Thriller","Director":"Bilal Lashari","Writer":"Hassan Rana","Actors":"Shaan Shahid, Hamza Abbasi, Shamoon Abbasi, Ayesha Khan","Plot":"The efforts of the Pakistani security forces in their fight against terrorism and how the lives of security officials are affected. A retired security officer returns to save Pakistan from a major terrorist attack.","Language":"English, Urdu","Country":"Pakistan","Awards":"10 wins.","Poster":"https://ia.media-imdb.com/images/M/MV5BMjI2NjM2MjYzMV5BMl5BanBnXkFtZTgwMjc0NTE1MDE@._V1_SX300.jpg","Ratings":[{"Source":"Internet Movie Database","Value":"8.2/10"}],"Metascore":"N/A","imdbRating":"8.2","imdbVotes":"28,553","imdbID":"tt1821700","Type":"movie","DVD":"N/A","BoxOffice":"N/A","Production":"N/A","Website":"N/A","Response":"True"}