{"Title":"Chasing Rainbows","Year":"2012","Rated":"N/A","Released":"02 Nov 2012","Runtime":"N/A","Genre":"Comedy","Director":"Dan Chisu","Writer":"Dan Chisu","Actors":"Adrian Titieni, Ionut Visan, Anca Florescu, Catalin Bordea","Plot":"A story about the illusion of getting rich in Romania. In a country where stories of striking it rich are everywhere, anyone thinks such a thing is not only possible, but it's easily ...","Language":"Romanian","Country":"Romania","Awards":"12 nominations.","Poster":"https://images-na.ssl-images-amazon.com/images/M/MV5BMjM5NTUzOTcxN15BMl5BanBnXkFtZTcwNjI4MTE2OA@@._V1_SX300.jpg","Ratings":[{"Source":"Internet Movie Database","Value":"7.1/10"}],"Metascore":"N/A","imdbRating":"7.1","imdbVotes":"383","imdbID":"tt1872167","Type":"movie","DVD":"N/A","BoxOffice":"N/A","Production":"N/A","Website":"N/A","Response":"True"}