{"Title":"Journey","Year":"2012","Rated":"N/A","Released":"N/A","Runtime":"96 min","Genre":"Drama","Director":"Malachi Roth","Writer":"Malachi Roth","Actors":"Theodore Bouloukos, Andrew Belcher, Jonathan Donahue, Kim Emerson","Plot":"A chain reaction of self-examination is triggered when a former covert operative turned sailing recluse decides to write a tell-all memoir and reconnect with his estranged son.","Language":"English","Country":"USA","Awards":"N/A","Poster":"http://ia.media-imdb.com/images/M/MV5BMTAwNzU3NjE4MTheQTJeQWpwZ15BbWU3MDE0MzE4MDg@._V1_SX300.jpg","Ratings":[],"Metascore":"N/A","imdbRating":"N/A","imdbVotes":"N/A","imdbID":"tt2186126","Type":"movie","DVD":"N/A","BoxOffice":"N/A","Production":"N/A","Website":"N/A","Response":"True"}