{"Title":"Find Your Body","Year":"2012","Rated":"N/A","Released":"18 Apr 2012","Runtime":"110 min","Genre":"Comedy","Director":"David Imedo","Writer":"Zviad Bliadze (story), Zviad Bliadze, David Imedo","Actors":"Tamar Basilia, Paata Guliashvili, Elene Imedashvili, Nanuka Jorjoliani","Plot":"N/A","Language":"Georgian","Country":"Georgia","Awards":"N/A","Poster":"http://ia.media-imdb.com/images/M/MV5BMTc5MjUwNTQ2MV5BMl5BanBnXkFtZTcwMTg2MDgwNw@@._V1_SX300.jpg","Ratings":[{"Source":"Internet Movie Database","Value":"6.7/10"}],"Metascore":"N/A","imdbRating":"6.7","imdbVotes":"7","imdbID":"tt2112328","Type":"movie","DVD":"N/A","BoxOffice":"N/A","Production":"N/A","Website":"N/A","Response":"True"}