{"Title":"The Bromley Boys","Year":"2014","Rated":"N/A","Released":"17 Dec 2014","Runtime":"N/A","Genre":"Comedy","Director":"Matt Lipsey","Writer":"Warren Dudley (screenplay)","Actors":"Alan Davies, Mark Dymond, Lars Arentz-Hansen, Hardeep Singh Kohli","Plot":"A boy, a girl, and the worst football team in Britain. You can't choose who you're going to fall in love with.","Language":"N/A","Country":"UK","Awards":"N/A","Poster":"http://ia.media-imdb.com/images/M/MV5BMTcyMzYyNzg4NV5BMl5BanBnXkFtZTgwNTA3ODU1MDE@._V1_SX300.jpg","Ratings":[],"Metascore":"N/A","imdbRating":"N/A","imdbVotes":"N/A","imdbID":"tt2179231","Type":"movie","DVD":"N/A","BoxOffice":"N/A","Production":"N/A","Website":"N/A","Response":"True"}