{"Title":"We Just Decided To","Year":"2012","Rated":"TV-MA","Released":"24 Jun 2012","Season":"1","Episode":"1","Runtime":"70 min","Genre":"Drama","Director":"Greg Mottola","Writer":"Aaron Sorkin (created by), Aaron Sorkin","Actors":"Jeff Daniels, Emily Mortimer, John Gallagher Jr., Alison Pill","Plot":"Will's professional idealism is put to the test with his new news team when they are first to cover the Deep Horizon platform oil spill.","Language":"English","Country":"USA","Awards":"N/A","Poster":"https://images-na.ssl-images-amazon.com/images/M/MV5BNTU1MDI3NjU0OV5BMl5BanBnXkFtZTcwMjY5NTUwOA@@._V1_SX300.jpg","Ratings":[{"Source":"Internet Movie Database","Value":"9.0/10"}],"Metascore":"N/A","imdbRating":"9.0","imdbVotes":"2318","imdbID":"tt2289479","seriesID":"tt1870479","Type":"episode","Response":"True"}