{"Title":"Raggedy DemAnn","Year":"2012","Rated":"N/A","Released":"18 Feb 2012","Runtime":"94 min","Genre":"Horror","Director":"Amanda Dyar","Writer":"Amanda Dyar, Kenny King","Actors":"Amanda Dyar, Kenny King, Elbert John Smith, Alissa Worley","Plot":"Every monster has their own beginning. For a troubled young woman named Carrie Ann, her nightmarish life is about to take an even more terrifying turn for the worse when she wanders into the wrong neck of the woods.","Language":"English","Country":"USA","Awards":"N/A","Poster":"N/A","Ratings":[{"Source":"Internet Movie Database","Value":"6.0/10"}],"Metascore":"N/A","imdbRating":"6.0","imdbVotes":"22","imdbID":"tt2279217","Type":"movie","DVD":"N/A","BoxOffice":"N/A","Production":"N/A","Website":"N/A","Response":"True"}