{"Title":"The Billionaire","Year":"2011","Rated":"N/A","Released":"20 Oct 2011","Runtime":"131 min","Genre":"Drama","Director":"Songyos Sugmakanan","Writer":"Nawapol Thamrongrattanarit (screenplay)","Actors":"Pachara Chirathivat, Walanlak Kumsuwan, Somboonsuk Niyomsiri","Plot":"What are you doing at his age? Age 16, TOP gained 400,000 Baht monthly from playing online games. Age 17, He was willing to fail school and instead earned money from selling chestnuts for ...","Language":"Thai","Country":"Thailand","Awards":"4 nominations.","Poster":"https://m.media-amazon.com/images/M/MV5BOGQ0ZDkzOGQtZTBiNi00ZGFlLWIxZWMtM2M0N2MyNmUzZGU2XkEyXkFqcGdeQXVyNDI3NjcxMDA@._V1_SX300.jpg","Ratings":[{"Source":"Internet Movie Database","Value":"7.9/10"}],"Metascore":"N/A","imdbRating":"7.9","imdbVotes":"1,185","imdbID":"tt2292955","Type":"movie","DVD":"N/A","BoxOffice":"N/A","Production":"N/A","Website":"N/A","Response":"True"}