{"Title":"Zakaas","Year":"2011","Rated":"N/A","Released":"30 Dec 2011","Runtime":"125 min","Genre":"Comedy","Director":"Ankush Choudhary","Writer":"Ankush Choudhary (screenplay), Nitin Dixit (screenplay)","Actors":"Ankush Choudhary, Jitendra Joshi, Sanjay Kapre, Amruta Khanvilkar","Plot":"A man with different names has relations with different woman who have helped him achieve success in life.","Language":"Marathi","Country":"India","Awards":"N/A","Poster":"N/A","Ratings":[{"Source":"Internet Movie Database","Value":"6.8/10"}],"Metascore":"N/A","imdbRating":"6.8","imdbVotes":"5","imdbID":"tt2396777","Type":"movie","DVD":"N/A","BoxOffice":"N/A","Production":"N/A","Website":"N/A","Response":"True"}