{"Title":"Through and Through","Year":"2012","Rated":"TV-MA","Released":"24 Aug 2012","Season":"2","Episode":"2","Runtime":"56 min","Genre":"Crime, Drama","Director":"Jean de Segonzac","Writer":"Farhad Safinia (creator), Bradford Winters, Angelina Burnett (executive story editor), Kevin J. Hynes (story)","Actors":"Kelsey Grammer, Connie Nielsen, Hannah Ware, Jeff Hephner","Plot":"Kane uses a tragedy in his personal life to further his political agenda and ultimately win control over the housing authority. Kane tries to remedy his fractured inner circle by poaching ...","Language":"English","Country":"USA","Awards":"N/A","Poster":"http://ia.media-imdb.com/images/M/MV5BMjAzNjI2MzI2Ml5BMl5BanBnXkFtZTgwNDcwNjg0MjE@._V1_SX300.jpg","Ratings":[{"Source":"Internet Movie Database","Value":"7.9/10"}],"Metascore":"N/A","imdbRating":"7.9","imdbVotes":"117","imdbID":"tt2324143","seriesID":"tt1833285","Type":"episode","Response":"True"}