{"Title":"At First Bite","Year":"2012","Rated":"N/A","Released":"N/A","Runtime":"97 min","Genre":"Comedy","Director":"Billy Nicholson, Jason Ungate","Writer":"Jason Ungate","Actors":"Jessica Evans, Sarah Bergh, Dave Cuomo, Asa Dyer","Plot":"When Brandon finds out his office crush Natalie has an obsession with vampire books, he does the only logical thing: pretends to be a real-life vampire in order to impress her. Too bad he ...","Language":"English","Country":"USA","Awards":"N/A","Poster":"N/A","Ratings":[],"Metascore":"N/A","imdbRating":"N/A","imdbVotes":"N/A","imdbID":"tt2322168","Type":"movie","DVD":"N/A","BoxOffice":"N/A","Production":"N/A","Website":"N/A","Response":"True"}