{"Title":"Bob Rest Ye Merry Gentle-Mannequins","Year":"2012","Rated":"TV-PG","Released":"16 Dec 2012","Season":"3","Episode":"9","Runtime":"30 min","Genre":"Animation, Comedy","Director":"Anthony Chun","Writer":"Loren Bouchard (created by), Loren Bouchard (developed by), Jim Dauterive (developed by), Kit Boss","Actors":"H. Jon Benjamin, Dan Mintz, Eugene Mirman, John Roberts","Plot":"'Tis the season for strange holiday mannequins.","Language":"English","Country":"N/A","Awards":"N/A","Poster":"http://ia.media-imdb.com/images/M/MV5BMTg2MzI0NTQ3OV5BMl5BanBnXkFtZTgwODMyMzc1MDE@._V1_SX300.jpg","Ratings":[{"Source":"Internet Movie Database","Value":"7.9/10"}],"Metascore":"N/A","imdbRating":"7.9","imdbVotes":"261","imdbID":"tt2531554","seriesID":"tt1561755","Type":"episode","Response":"True"}