{"Title":"Scared and Running","Year":"2013","Rated":"TV-14","Released":"23 Jun 2013","Season":"3","Episode":"5","Runtime":"44 min","Genre":"Crime, Drama, Mystery","Director":"Daniel Attias","Writer":"Veena Sud (developer), Coleman Herbert","Actors":"Mireille Enos, Joel Kinnaman, Elias Koteas, Hugh Dillon","Plot":"Kallie's mother Danette tells her boyfriend Joe Mills that she's starting to worry about Kallie. He tells her she has nothing to worry about. The police continue their search for Joe. Mama ...","Language":"English","Country":"N/A","Awards":"N/A","Poster":"https://images-na.ssl-images-amazon.com/images/M/MV5BMTM5NjYyNzEzNl5BMl5BanBnXkFtZTcwOTA2NDg3OQ@@._V1_SX300.jpg","Ratings":[{"Source":"Internet Movie Database","Value":"8.4/10"}],"Metascore":"N/A","imdbRating":"8.4","imdbVotes":"502","imdbID":"tt2722616","seriesID":"tt1637727","Type":"episode","Response":"True"}