{"Title":"Rh11","Year":"2010","Rated":"N/A","Released":"17 Jan 2010","Runtime":"95 min","Genre":"Drama","Director":"Callum Andrew Johnston","Writer":"Jack Gadd, Callum Andrew Johnston (created by)","Actors":"Jack Gadd, Michael Oram, Billy Lenson, Ali Storm","Plot":"RH11 is a story about six close friends, who have grown up together on a rough estate. When they come to the age of sixteen, the friends have a choice to make, do they choose a life of ...","Language":"English","Country":"UK","Awards":"N/A","Poster":"http://ia.media-imdb.com/images/M/MV5BMTczNzEzNjc5Ml5BMl5BanBnXkFtZTgwMzI4NjIzMjE@._V1_SX300.jpg","Ratings":[],"Metascore":"N/A","imdbRating":"N/A","imdbVotes":"N/A","imdbID":"tt2848326","Type":"movie","DVD":"N/A","BoxOffice":"N/A","Production":"N/A","Website":"N/A","Response":"True"}