{"Title":"Red Team III","Year":"2013","Rated":"TV-MA","Released":"25 Aug 2013","Season":"2","Episode":"7","Runtime":"58 min","Genre":"Drama","Director":"Anthony Hemingway","Writer":"Aaron Sorkin (created by), Aaron Sorkin, Corinne Kingsbury (story editor), Brendan Fehily (story editor), Ian Reichbach (executive story editor), Camilla Blackett (staff writer), Michael Gunn (story editor), Dana Ledoux Miller (story editor), Adam R. Perlman (staff writer), Elizabeth Peterson (staff writer), Matthew Lopez (staff writer)","Actors":"Jeff Daniels, Emily Mortimer, John Gallagher Jr., Alison Pill","Plot":"In the aftermath of ACN's Operation Genoa report, the staff who put it together face some serious blowback, not just when the government responds but also when the sources' credibility comes into question.","Language":"English","Country":"USA","Awards":"N/A","Poster":"https://images-na.ssl-images-amazon.com/images/M/MV5BNDIxMzkxNDQ1Ml5BMl5BanBnXkFtZTgwOTk5OTQzMzE@._V1_SX300.jpg","Ratings":[{"Source":"Internet Movie Database","Value":"9.1/10"}],"Metascore":"N/A","imdbRating":"9.1","imdbVotes":"1087","imdbID":"tt3067860","seriesID":"tt1870479","Type":"episode","Response":"True"}