{"Title":"Dance Back from the Grave","Year":"2014","Rated":"TV-PG","Released":"28 Jan 2014","Season":"1","Episode":"12","Runtime":"42 min","Genre":"Drama, Fantasy, Horror","Director":"Rob Hardy","Writer":"Julie Plec (created by), Michael Russo, Michael Narducci, Michelle Paradise (executive story editor), Charlie Charbonneau (story editor), L.J. Smith (based in part on the character Klaus from \"The Vampire Diaries\" novels by), Marguerite MacIntyre (staff writer)","Actors":"Joseph Morgan, Daniel Gillies, Claire Holt, Phoebe Tonkin","Plot":"Marcel, still angered refuses to help Klaus when a gruesome discovery is made. Rebekah is on alert when she uncovers the remnants of a sacrifice down by the docks realizing it's the work of...","Language":"English","Country":"USA","Awards":"N/A","Poster":"https://images-na.ssl-images-amazon.com/images/M/MV5BMjIxMTY5MTExM15BMl5BanBnXkFtZTgwMDUzODUwMTE@._V1_SX300.jpg","Ratings":[{"Source":"Internet Movie Database","Value":"9.0/10"}],"Metascore":"N/A","imdbRating":"9.0","imdbVotes":"917","imdbID":"tt3188842","seriesID":"tt2632424","Type":"episode","Response":"True"}