{"Title":"Uyyala Jampala","Year":"2013","Rated":"N/A","Released":"25 Dec 2013","Runtime":"124 min","Genre":"Drama, Family, Romance","Director":"Virinchi Varma","Writer":"Ram Mohan P., Raj Tarun (dialogue & screenplay), Virinchi Varma","Actors":"Raj Tarun, Avika Gor, Punarnavi Bhupalam, Kireeti Damaraju","Plot":"A romantic entertainer between a \"bava\" and a \"maradalu\" set in a contemporary coastal town.","Language":"Telugu","Country":"India","Awards":"3 nominations.","Poster":"https://images-na.ssl-images-amazon.com/images/M/MV5BNGVhMGZlNWUtZjc3Yi00MGUxLWFhNTAtMWZjNDVjMjNmZjUxXkEyXkFqcGdeQXVyNjUxMzQyMzg@._V1_SX300.jpg","Ratings":[{"Source":"Internet Movie Database","Value":"7.3/10"}],"Metascore":"N/A","imdbRating":"7.3","imdbVotes":"725","imdbID":"tt3290676","Type":"movie","DVD":"N/A","BoxOffice":"N/A","Production":"N/A","Website":"N/A","Response":"True"}