{"Title":"Liver, I Hardly Know Her","Year":"2014","Rated":"TV-MA","Released":"23 Mar 2014","Season":"4","Episode":"10","Runtime":"51 min","Genre":"Comedy, Drama","Director":"Christopher Chulack","Writer":"John Wells (developer), Paul Abbott (creator), Davey Holmes","Actors":"William H. Macy, Emmy Rossum, Jeremy Allen White, Ethan Cutkosky","Plot":"Fiona goes on a heavy bender and ends up in Wisconsin and Lip has to come rescue her. Mickey and Kev start fighting over their joint venture. Bonnie and Carl steal a car. Sammi and Sheila try to find Frank a cheap liver transplant.","Language":"English","Country":"N/A","Awards":"N/A","Poster":"https://images-na.ssl-images-amazon.com/images/M/MV5BMjE1OTM2NTg3MV5BMl5BanBnXkFtZTgwMTk4ODYyNzE@._V1_SX300.jpg","Ratings":[{"Source":"Internet Movie Database","Value":"9.0/10"}],"Metascore":"N/A","imdbRating":"9.0","imdbVotes":"1143","imdbID":"tt3507322","seriesID":"tt1586680","Type":"episode","Response":"True"}