{"Title":"Uber Ray","Year":"2014","Rated":"TV-MA","Released":"20 Jul 2014","Season":"2","Episode":"2","Runtime":"54 min","Genre":"Crime, Drama","Director":"Michael Uppendahl","Writer":"Ann Biderman, David Hollander, Ann Biderman (created by)","Actors":"Liev Schreiber, Paula Malcomson, Eddie Marsan, Dash Mihok","Plot":"Ray forces Mickey to return to LA. A reporter investigates Sully's death.","Language":"English","Country":"USA","Awards":"N/A","Poster":"https://ia.media-imdb.com/images/M/MV5BMTQzNjMzMjk5NV5BMl5BanBnXkFtZTgwMjQ1NDIxMjE@._V1_SX300.jpg","Ratings":[{"Source":"Internet Movie Database","Value":"8.2/10"}],"Metascore":"N/A","imdbRating":"8.2","imdbVotes":"629","imdbID":"tt3564604","seriesID":"tt2249007","Type":"episode","Response":"True"}