{"Title":"A Death in the Family","Year":"2015","Rated":"TV-MA","Released":"09 Mar 2015","Season":"3","Episode":"1","Runtime":"43 min","Genre":"Drama, Horror, Mystery","Director":"Tucker Gates","Writer":"Carlton Cuse (developed for television by), Kerry Ehrin (developed for television by), Anthony Cipriano (developed for television by), Carlton Cuse, Kerry Ehrin, Robert Bloch (based on characters from the novel 'Psycho' by)","Actors":"Vera Farmiga, Freddie Highmore, Max Thieriot, Olivia Cooke","Plot":"Norman and Emma make decisions regarding their future; Norma informs Norman of his boundaries.","Language":"English","Country":"USA","Awards":"N/A","Poster":"https://images-na.ssl-images-amazon.com/images/M/MV5BNDA5NTE2NTA3MF5BMl5BanBnXkFtZTgwNDcxNzk0NDE@._V1_SX300.jpg","Ratings":[{"Source":"Internet Movie Database","Value":"8.5/10"}],"Metascore":"N/A","imdbRating":"8.5","imdbVotes":"891","imdbID":"tt3654480","seriesID":"tt2188671","Type":"episode","Response":"True"}