{"Title":"The Watch","Year":"2015","Rated":"TV-MA","Released":"02 May 2015","Season":"1","Episode":"13","Runtime":"57 min","Genre":"Drama, Romance, Sci-Fi","Director":"Metin Hüseyin","Writer":"Diana Gabaldon (based on the series of books written by), Ronald D. Moore (developed by), Toni Graphia (written for television by)","Actors":"Caitriona Balfe, Sam Heughan, Laura Donnelly, Douglas Henshall","Plot":"A Redcoat deserter from Jamie's past returns; Jenny goes into labor; Jamie and Ian join the Watch.","Language":"English","Country":"USA","Awards":"N/A","Poster":"https://images-na.ssl-images-amazon.com/images/M/MV5BMjI4NDQyNDQwNF5BMl5BanBnXkFtZTgwNTgwNTM1NTE@._V1_SX300.jpg","Ratings":[{"Source":"Internet Movie Database","Value":"8.7/10"}],"Metascore":"N/A","imdbRating":"8.7","imdbVotes":"1553","imdbID":"tt3889026","seriesID":"tt3006802","Type":"episode","Response":"True"}