{"Title":"Apothecary","Year":"2014","Rated":"N/A","Released":"07 Aug 2014","Runtime":"138 min","Genre":"Drama, Thriller","Director":"Madhav Ramadasan","Writer":"Hemanth Kumar, Madhav Ramadasan","Actors":"Suresh Gopi, Jayasurya, Abhirami, Asif Ali","Plot":"A doctor is haunted by his conscience, when puppeteer-ed by his superiors.","Language":"Malayalam","Country":"India","Awards":"1 win.","Poster":"https://images-na.ssl-images-amazon.com/images/M/MV5BMTgzODYzNzQ2NV5BMl5BanBnXkFtZTgwMjAwMjgwNzE@._V1_SX300.jpg","Ratings":[{"Source":"Internet Movie Database","Value":"7.1/10"}],"Metascore":"N/A","imdbRating":"7.1","imdbVotes":"402","imdbID":"tt3951566","Type":"movie","DVD":"N/A","BoxOffice":"N/A","Production":"N/A","Website":"N/A","Response":"True"}