{"Title":"The DVD","Year":"2011","Rated":"TV-Y7","Released":"03 May 2011","Season":"1","Episode":"1","Runtime":"23 min","Genre":"Animation, Comedy, Family","Director":"Mic Graves","Writer":"Benjamin Bocquelet, Jon Foster, James Lamont","Actors":"J.R. Richard","Plot":"Gumball and Darwin try to get out of returning a rented DVD when they accidentally destroy it.","Language":"N/A","Country":"N/A","Awards":"N/A","Poster":"https://images-na.ssl-images-amazon.com/images/M/MV5BMTU1ODdhNmUtYzZkZC00NmNiLTg5ODAtZjU5OGMzYjQ5MmQwXkEyXkFqcGdeQXVyNjQyMzg3MTE@._V1_SX300.jpg","Ratings":[{"Source":"Internet Movie Database","Value":"8.5/10"}],"Metascore":"N/A","imdbRating":"8.5","imdbVotes":"108","imdbID":"tt4077848","seriesID":"tt1942683","Type":"episode","Response":"True"}