{"Title":"Window Connection","Year":"2014","Rated":"N/A","Released":"09 May 2014","Runtime":"N/A","Genre":"Drama","Director":"R.K. Gupta","Writer":"N/A","Actors":"Aryann Bhowmick, Biswajit Chakraborty, Tanushree Chakraborty, Rajat Ganguly","Plot":"N/A","Language":"Bengali","Country":"India","Awards":"N/A","Poster":"N/A","Ratings":[{"Source":"Internet Movie Database","Value":"8.1/10"}],"Metascore":"N/A","imdbRating":"8.1","imdbVotes":"7","imdbID":"tt4108092","Type":"movie","DVD":"N/A","BoxOffice":"N/A","Production":"N/A","Website":"N/A","Response":"True"}