{"Title":"BoJack Horseman Christmas Special: Sabrina's Christmas Wish","Year":"2014","Rated":"TV-MA","Released":"19 Dec 2014","Season":"2","Episode":"0","Runtime":"25 min","Genre":"Animation, Comedy, Drama","Director":"Joel Moser","Writer":"Raphael Bob-Waksberg (creator), Raphael Bob-Waksberg","Actors":"Will Arnett, Amy Sedaris, Alison Brie, Aaron Paul","Plot":"BoJack and Todd watch a very special Christmas episode of \"Horsin' Around\" to celebrate the holidays.","Language":"English","Country":"USA","Awards":"N/A","Poster":"https://images-na.ssl-images-amazon.com/images/M/MV5BMjAwNzI2OTM2Ml5BMl5BanBnXkFtZTgwNzI0NjQzNjE@._V1_SX300.jpg","Ratings":[{"Source":"Internet Movie Database","Value":"7.0/10"}],"Metascore":"N/A","imdbRating":"7.0","imdbVotes":"874","imdbID":"tt4294938","seriesID":"tt3398228","Type":"episode","Response":"True"}