{"Title":"Nabab Nandini","Year":"2007","Rated":"N/A","Released":"23 Jan 2007","Runtime":"120 min","Genre":"Comedy, Romance","Director":"Haranath Chakraborty","Writer":"Anjan Choudhury","Actors":"Hiran Chatterjee, Koyel Mallick, Ranjit Mallick, Sagnik Chatterjee","Plot":"N/A","Language":"Bengali","Country":"India","Awards":"N/A","Poster":"https://images-na.ssl-images-amazon.com/images/M/MV5BMjFmY2NlYTItOThmYS00Nzg0LWFhYjgtNDIxNzQyZjFhZjQzXkEyXkFqcGdeQXVyODM0ODQ5NDM@._V1_SX300.jpg","Ratings":[{"Source":"Internet Movie Database","Value":"8.0/10"}],"Metascore":"N/A","imdbRating":"8.0","imdbVotes":"11","imdbID":"tt4771774","Type":"movie","DVD":"N/A","BoxOffice":"N/A","Production":"N/A","Website":"N/A","Response":"True"}