{"Title":"Prey","Year":"2016","Rated":"N/A","Released":"17 Jan 2016","Season":"3","Episode":"3","Runtime":"89 min","Genre":"Crime, Drama, Mystery","Director":"Lawrence Gough","Writer":"Colin Dexter (characters), Russell Lewis (written and devised by)","Actors":"Stefanie Martini, Amy McCallum, Darrell D'Silva, Rob Callender","Plot":"The detectives are called in to deal with the case of a missing au pair who disappeared after her evening class at Night School.","Language":"English","Country":"UK","Awards":"N/A","Poster":"https://m.media-amazon.com/images/M/MV5BZTgwMzczMTItNDQwMS00YzJmLWIwNjYtNTUxMTI2NWZmODQ2XkEyXkFqcGdeQXVyMjExMjk0ODk@._V1_SX300.jpg","Ratings":[{"Source":"Internet Movie Database","Value":"8.2/10"}],"Metascore":"N/A","imdbRating":"8.2","imdbVotes":"518","imdbID":"tt4839470","seriesID":"tt2701582","Type":"episode","Response":"True"}