{"Title":"A Copy of My Mind","Year":"2015","Rated":"N/A","Released":"03 Jun 2016","Runtime":"116 min","Genre":"Drama","Director":"Joko Anwar","Writer":"Joko Anwar","Actors":"Tara Basro, Chicco Jerikho, Maera Panigoro, Paul Agusta","Plot":"A female cheap salon worker and a pirated DVDs subtitle maker fall in love during the turbulent presidential election in Indonesia.","Language":"Indonesian, English","Country":"Indonesia, South Korea","Awards":"1 win & 3 nominations.","Poster":"https://m.media-amazon.com/images/M/MV5BMTg4MzQwNzAyNV5BMl5BanBnXkFtZTgwNTEyMDA5NzE@._V1_SX300.jpg","Ratings":[{"Source":"Internet Movie Database","Value":"7.4/10"}],"Metascore":"N/A","imdbRating":"7.4","imdbVotes":"479","imdbID":"tt4911656","Type":"movie","DVD":"N/A","BoxOffice":"N/A","Production":"N/A","Website":"N/A","Response":"True"}