{"Title":"First Blood","Year":"2016","Rated":"N/A","Released":"10 May 2016","Season":"4","Episode":"1","Runtime":"45 min","Genre":"Crime, Drama","Director":"Kevin Carlin","Writer":"John Ridley, Reg Watson (creator), Darren Chau (inspired by an idea from)","Actors":"Danielle Cormack, Kate Atkinson, Celia Ireland, Shareena Clanton","Plot":"N/A","Language":"N/A","Country":"N/A","Awards":"N/A","Poster":"http://ia.media-imdb.com/images/M/MV5BMjM4NTM1ODQ2MF5BMl5BanBnXkFtZTgwMzY1OTM3MzE@._V1_SX300.jpg","Ratings":[{"Source":"Internet Movie Database","Value":"9.6/10"}],"Metascore":"N/A","imdbRating":"9.6","imdbVotes":"50","imdbID":"tt5064954","seriesID":"tt2433738","Type":"episode","Response":"True"}