{"Title":"Tape 4, Side A","Year":"2017","Rated":"TV-MA","Released":"31 Mar 2017","Season":"1","Episode":"7","Runtime":"53 min","Genre":"Drama, Mystery","Director":"Gregg Araki","Writer":"Elizabeth Benjamin (teleplay by), Brian Yorkey (created for television by), Jay Asher (based upon the book by), Nic Sheff (story editor)","Actors":"Dylan Minnette, Katherine Langford, Christian Navarro, Alisha Boe","Plot":"Another student sabotages Hannah during a class project. Clay's nightmares about Hannah spill over into the daytime.","Language":"English","Country":"N/A","Awards":"N/A","Poster":"https://images-na.ssl-images-amazon.com/images/M/MV5BNTQzNDI0MDg2OF5BMl5BanBnXkFtZTgwMDIzNTQwMjI@._V1_SX300.jpg","Ratings":[{"Source":"Internet Movie Database","Value":"8.4/10"}],"Metascore":"N/A","imdbRating":"8.4","imdbVotes":"3588","imdbID":"tt5174262","seriesID":"tt1837492","Type":"episode","Response":"True"}