{"Title":"What's My Motivation","Year":"2017","Rated":"N/A","Released":"12 Jan 2017","Season":"1","Episode":"11","Runtime":"24 min","Genre":"Comedy, Drama, Fantasy, Romance","Director":"Lynn Shelton","Writer":"Michael Schur (created by), Andrew Law","Actors":"Kristen Bell, William Jackson Harper, Jameela Jamil, D'Arcy Carden","Plot":"Eleanor and Tahani hatch a plan as Michael makes a surprising discovery. Chidi confides in Eleanor when he learns some interesting news.","Language":"English","Country":"USA","Awards":"N/A","Poster":"https://m.media-amazon.com/images/M/MV5BM2E2YzcxMWItMTkxZi00Mjk0LTg5ZGUtZDQyNmE2ODE2YmY2XkEyXkFqcGdeQXVyMjg2MTMyNTM@._V1_SX300.jpg","Ratings":[{"Source":"Internet Movie Database","Value":"8.4/10"}],"Metascore":"N/A","imdbRating":"8.4","imdbVotes":"1223","imdbID":"tt5884088","seriesID":"tt4955642","Type":"episode","Response":"True"}