{"Title":"Love You Baba","Year":"2014","Rated":"N/A","Released":"12 Dec 2014","Runtime":"N/A","Genre":"Drama","Director":"Saugat Bista","Writer":"N/A","Actors":"N/A","Plot":"Nepali movie 'Love You Baba' is an unique movie in the world - directed by an 8-years-old director. The director win the World Record an being the youngest film director in the world.","Language":"Nepali","Country":"Nepal","Awards":"N/A","Poster":"https://images-na.ssl-images-amazon.com/images/M/MV5BY2FjNDIzMWQtMmZmNy00ZDAzLWFmY2YtYjQyYzA1NGYxYzE2XkEyXkFqcGdeQXVyNjgxOTU1ODI@._V1_SX300.jpg","Ratings":[],"Metascore":"N/A","imdbRating":"N/A","imdbVotes":"N/A","imdbID":"tt5954644","Type":"movie","DVD":"N/A","BoxOffice":"N/A","Production":"N/A","Website":"N/A","Response":"True"}