{"Title":"Kalebegiak","Year":"2016","Rated":"N/A","Released":"14 Oct 2016","Runtime":"116 min","Genre":"Comedy, Drama","Director":"Daniel Calparsoro, Iñaki Camacho, Borja Cobeaga, María Elorza, Maider Férnandez, Isabel Herguera, Ekain Irigoien, Julio Medem, Gracia Querejeta, Luiso Berdejo","Writer":"Luiso Berdejo, Michel Gaztambide (creator), Jorge Gil Munarriz (creator)","Actors":"Marta Etura, Bárbara Goenaga, Miren Ibarguren, Kandido Uranga","Plot":"N/A","Language":"Basque, Spanish, English","Country":"Spain","Awards":"N/A","Poster":"https://images-na.ssl-images-amazon.com/images/M/MV5BMDNhYmM5MmItNDYzMS00OWFkLTk4NTMtYjBhNWRjNDgyZTMzXkEyXkFqcGdeQXVyNjg5Njc4MjM@._V1_SX300.jpg","Ratings":[],"Metascore":"N/A","imdbRating":"N/A","imdbVotes":"N/A","imdbID":"tt6056072","Type":"movie","DVD":"N/A","BoxOffice":"N/A","Production":"N/A","Website":"N/A","Response":"True"}