{"Title":"Preboot","Year":"2016","Rated":"TV-PG","Released":"19 Nov 2016","Season":"7","Episode":"38","Runtime":"11 min","Genre":"Animation, Adventure, Comedy","Director":"Adam Muto","Writer":"Aleks Sennwald, Adam Muto, Kent Osborne (story), Jack Pendarvis (story), Ashly Burch (story), Adam Muto (story)","Actors":"Jeremy Shada, John DiMaggio, Jackie Buscarino, Collin Dean","Plot":"While searching for old human artifacts, Jake, Finn, and Susan Strong meet Tiffany, who is employed by a mysterious Doctor Gross.","Language":"N/A","Country":"N/A","Awards":"N/A","Poster":"https://images-na.ssl-images-amazon.com/images/M/MV5BMjE2MzE1MDI2M15BMl5BanBnXkFtZTgwNzUyODQxMDE@._V1_SX300.jpg","Ratings":[{"Source":"Internet Movie Database","Value":"7.8/10"}],"Metascore":"N/A","imdbRating":"7.8","imdbVotes":"36","imdbID":"tt6186784","seriesID":"tt1305826","Type":"episode","Response":"True"}