{"Title":"The Reckoning","Year":"2017","Rated":"TV-14","Released":"01 Feb 2017","Season":"4","Episode":"20","Runtime":"44 min","Genre":"Action, Drama, History","Director":"Ben Bolt","Writer":"Michael Hirst (created by), Michael Hirst","Actors":"Katheryn Winnick, Gustaf Skarsgård, Alexander Ludwig, Peter Franzén","Plot":"Prince Aethelwulf finds himself subject to the Vikings' battle master plan; Ecbert remains behind with a plan of his own.","Language":"N/A","Country":"N/A","Awards":"N/A","Poster":"https://images-na.ssl-images-amazon.com/images/M/MV5BZjM0YWU2YTQtZTUzNy00Njk5LTgyNDAtYmU4MDE4OTU4NzRkL2ltYWdlXkEyXkFqcGdeQXVyNjc5Mjg0NjU@._V1_SX300.jpg","Ratings":[{"Source":"Internet Movie Database","Value":"8.6/10"}],"Metascore":"N/A","imdbRating":"8.6","imdbVotes":"1872","imdbID":"tt6315234","seriesID":"tt2306299","Type":"episode","Response":"True"}