{"Title":"Juliya","Year":"2009","Rated":"N/A","Released":"18 Jul 2009","Runtime":"95 min","Genre":"Action, Romance","Director":"Sampath Sri Roshan","Writer":"Nishantha Weerasingha","Actors":"Sampath Sri Roshan, Nadeesha Hemamali, Sasanthi Jayasekara, Charith Abeysinghe","Plot":"Julia, the innocent and naive young woman enjoying the bliss of youth is fascinated, like any other girl of her age, by trendy and handsome young men.Unfortunately for her, the youth who ...","Language":"Sinhalese","Country":"Sri Lanka","Awards":"N/A","Poster":"https://m.media-amazon.com/images/M/MV5BNTk3OGE1MGEtZGU2Yy00MDE3LTllYmItYjYxMTZlNWE4YzFmXkEyXkFqcGdeQXVyNDMwOTc5MDg@._V1_SX300.jpg","Ratings":[{"Source":"Internet Movie Database","Value":"8.0/10"}],"Metascore":"N/A","imdbRating":"8.0","imdbVotes":"7","imdbID":"tt7643202","Type":"movie","DVD":"N/A","BoxOffice":"N/A","Production":"N/A","Website":"N/A","Response":"True"}