{"Title":"Mental Madhilo","Year":"2017","Rated":"N/A","Released":"24 Nov 2017","Runtime":"N/A","Genre":"Comedy, Drama, Romance","Director":"Vivek Athreya","Writer":"Vivek Athreya","Actors":"Sree Vishnu, Nivetha Pethuraj, Amrutha Srinivasan, Sivaji Raja","Plot":"An indecisive guy who has been rejected by several women, finds himself in a spot when he has to choose between two women.","Language":"Telugu","Country":"India","Awards":"N/A","Poster":"https://ia.media-imdb.com/images/M/MV5BMTc5YWJmYTYtMmE1Mi00NDA3LTlhYWMtMTE3NTRjMjEwMjQ0XkEyXkFqcGdeQXVyMzYxOTQ3MDg@._V1_SX300.jpg","Ratings":[{"Source":"Internet Movie Database","Value":"7.5/10"}],"Metascore":"N/A","imdbRating":"7.5","imdbVotes":"175","imdbID":"tt7675422","Type":"movie","DVD":"N/A","BoxOffice":"N/A","Production":"-none","Website":"N/A","Response":"True"}