{"Title":"Mission Impos-Slug-Ble","Year":"2018","Rated":"TV-PG","Released":"20 May 2018","Season":"8","Episode":"20","Runtime":"22 min","Genre":"Animation, Comedy","Director":"Bernard Derriman, Chris Song","Writer":"Loren Bouchard (created by), Loren Bouchard (developed by), Jim Dauterive (developed by), Nora Smith","Actors":"H. Jon Benjamin, Dan Mintz, Eugene Mirman, Larry Murphy","Plot":"Louise devises a plan to get her extensive Burobu card collection back after it's confiscated at school.","Language":"English","Country":"N/A","Awards":"N/A","Poster":"https://m.media-amazon.com/images/M/MV5BOWYyYTA0MTItNTVmZC00ZDY2LWJhMTMtMTE4YzMwYzE4ZDJmXkEyXkFqcGdeQXVyNTAyODkwOQ@@._V1_SX300.jpg","Ratings":[{"Source":"Internet Movie Database","Value":"7.4/10"}],"Metascore":"N/A","imdbRating":"7.4","imdbVotes":"118","imdbID":"tt8259898","seriesID":"tt1561755","Type":"episode","Response":"True"}