{"Title":"Gujarati Wedding in Goa","Year":"2018","Rated":"N/A","Released":"30 Mar 2018","Runtime":"130 min","Genre":"Comedy, Family","Director":"Ronny Rajhit","Writer":"Ronny Rajhit","Actors":"Garima Bhardwaj, Geet Brahmbhatt, Shivang Brahmbhatt, Jay Khetani","Plot":"N/A","Language":"None","Country":"India","Awards":"N/A","Poster":"https://m.media-amazon.com/images/M/MV5BYmE5ODNjNzAtZGQ1Ny00ODk0LThlYzQtZjZlNTkxN2I2ZmMwXkEyXkFqcGdeQXVyMTk5NjM4Mjc@._V1_SX300.jpg","Ratings":[{"Source":"Internet Movie Database","Value":"8.8/10"}],"Metascore":"N/A","imdbRating":"8.8","imdbVotes":"5","imdbID":"tt8216392","Type":"movie","DVD":"N/A","BoxOffice":"N/A","Production":"N/A","Website":"N/A","Response":"True"}