{"Title":"Mo Mommy Mo Problems","Year":"2018","Rated":"TV-PG","Released":"13 May 2018","Season":"8","Episode":"19","Runtime":"22 min","Genre":"Animation, Comedy","Director":"Bernard Derriman, Ian Hamilton","Writer":"Loren Bouchard (created by), Loren Bouchard (developed by), Jim Dauterive (developed by), Steven Davis","Actors":"H. Jon Benjamin, Dan Mintz, Eugene Mirman, John Roberts","Plot":"On Mother's Day, the Belchers wind up in a real estate scheme when attend open houses for free food and Linda meets a charming real estate agent.","Language":"English","Country":"N/A","Awards":"N/A","Poster":"https://m.media-amazon.com/images/M/MV5BYmRlMDBmMDgtMDc5Mi00YmU0LTg1ZDQtZWIyMjAyYTIwNDIwXkEyXkFqcGdeQXVyNTAyODkwOQ@@._V1_SX300.jpg","Ratings":[{"Source":"Internet Movie Database","Value":"7.7/10"}],"Metascore":"N/A","imdbRating":"7.7","imdbVotes":"127","imdbID":"tt8259896","seriesID":"tt1561755","Type":"episode","Response":"True"}